aioeasysqlite/__init__.py
aioeasysqlite/db.py
aioeasysqlite/exceptions.py
aioeasysqlite-1.1.2.dist-info/METADATA
aioeasysqlite-1.1.2.dist-info/WHEEL
aioeasysqlite-1.1.2.dist-info/licenses/LICENSE
aioeasysqlite-1.1.2.dist-info/RECORD
