Metadata-Version: 2.4
Name: aioeasysqlite
Version: 1.1.2
Summary: Library for easy work with databases. Easier aiosqlite version.
Project-URL: Homepage, https://github.com/treizd/AioEasySqlite/tree/master
Project-URL: Issues, https://github.com/treizd/AioEasySqlite/issues
Author-email: treizd <sqeshexaero@gmail.com>
License-File: LICENSE
Classifier: License :: OSI Approved :: MIT License
Classifier: Operating System :: OS Independent
Classifier: Programming Language :: Python :: 3
Requires-Python: >=3.5.0
Requires-Dist: aiosqlite>=0.16.0
